demand_ai/__init__.py
demand_ai/assets.py
demand_ai/client.py
demand_ai/client_state.py
demand_ai/model.py
demand_ai/prediction.py
demand_ai-0.9.1.dist-info/WHEEL
demand_ai-0.9.1.dist-info/METADATA
demand_ai-0.9.1.dist-info/RECORD
