Metadata-Version: 2.3
Name: demand-ai
Version: 0.9.1
Summary: Demand-AI client library
Requires-Dist: pandas>=2.3.3
Requires-Dist: pydantic>=2.12.4
Requires-Dist: requests>=2.32.5
Requires-Python: >=3.10, <3.14
